rtl/sync2ff.sv
module sync2ff #(
    parameter int W = 1
)(
    input logic clk,
    input logic rst_n,
    input logic [W-1:0] d,
    output logic [W-1:0] q
);

    logic [W-1:0] q1;

    always_ff @(posedge clk or negedge rst_n) begin
        if (!rst_n) begin
            q1 <= '0;
            q  <= '0;
        end else begin
            q1 <= d;
            q  <= q1;
        end
    end
endmodule

rtl/fifo_async.sv
`timescale 1ns/1ps

module fifo_async #(
    parameter int DW    = 8,
    parameter int DEPTH = 8
)(
    // write domain
    input  logic          w_clk,
    input  logic          w_rst_n,
    input  logic          w_en,
    input  logic [DW-1:0] w_data,
    output logic          full,

    // read domain
    input  logic          r_clk,
    input  logic          r_rst_n,
    input  logic          r_en,
    output logic [DW-1:0] r_data,
    output logic          empty
);

    localparam int AW = $clog2(DEPTH);
    // pointers have one extra bit for full/empty detection
    localparam int PW = AW + 1;

    // memory
    logic [DW-1:0] mem [0:DEPTH-1];

    // binary + gray pointers
    logic [PW-1:0] w_bin,  w_bin_next;
    logic [PW-1:0] w_gray, w_gray_next;

    logic [PW-1:0] r_bin,  r_bin_next;
    logic [PW-1:0] r_gray, r_gray_next;

    // synchronized gray pointers across domains
    logic [PW-1:0] r_gray_sync_w;
    logic [PW-1:0] w_gray_sync_r;

    // next flags (registered flags break combinational loops)
    logic full_next;
    logic empty_next;

    // increment enables (use registered full/empty)
    logic w_inc;
    logic r_inc;

    // ----------------------------
    // helper: bin -> gray (sized)
    // ----------------------------
    function automatic logic [PW-1:0] bin2gray(input logic [PW-1:0] b);
        return (b >> 1) ^ b;
    endfunction

    // ============================================================
    // WRITE DOMAIN
    // ============================================================

    assign w_inc      = w_en && !full;
    assign w_bin_next = w_bin + {{(PW-1){1'b0}}, w_inc};
    assign w_gray_next = bin2gray(w_bin_next);

    // sync read gray pointer into write clock domain
    sync2ff #(.W(PW)) u_sync_rptr_to_w (
        .clk  (w_clk),
        .rst_n(w_rst_n),
        .d    (r_gray),
        .q    (r_gray_sync_w)
    );

    // FULL detection compare: invert top two bits of synced read pointer
    logic [PW-1:0] w_gray_full_cmp;
    always_comb begin
        w_gray_full_cmp = r_gray_sync_w;
        w_gray_full_cmp[PW-1 -: 2] = ~r_gray_sync_w[PW-1 -: 2];
    end

    assign full_next = (w_gray_next == w_gray_full_cmp);

    // write memory + update pointers
    always_ff @(posedge w_clk or negedge w_rst_n) begin
        if (!w_rst_n) begin
            w_bin  <= '0;
            w_gray <= '0;
        end else begin
            if (w_inc) begin
                mem[w_bin[AW-1:0]] <= w_data;
            end
            w_bin  <= w_bin_next;
            w_gray <= w_gray_next;
        end
    end

    // register FULL flag (breaks comb loop)
    always_ff @(posedge w_clk or negedge w_rst_n) begin
        if (!w_rst_n) full <= 1'b0;
        else          full <= full_next;
    end

    // ============================================================
    // READ DOMAIN
    // ============================================================

    assign r_inc      = r_en && !empty;
    assign r_bin_next = r_bin + {{(PW-1){1'b0}}, r_inc};
    assign r_gray_next = bin2gray(r_bin_next);

    // sync write gray pointer into read clock domain
    sync2ff #(.W(PW)) u_sync_wptr_to_r (
        .clk  (r_clk),
        .rst_n(r_rst_n),
        .d    (w_gray),
        .q    (w_gray_sync_r)
    );

    assign empty_next = (r_gray_next == w_gray_sync_r);

    // read memory + update pointers/data
    always_ff @(posedge r_clk or negedge r_rst_n) begin
        if (!r_rst_n) begin
            r_bin  <= '0;
            r_gray <= '0;
            r_data <= '0;
        end else begin
            if (r_inc) begin
                r_data <= mem[r_bin[AW-1:0]];
            end
            r_bin  <= r_bin_next;
            r_gray <= r_gray_next;
        end
    end

    // register EMPTY flag (breaks comb loop)
    always_ff @(posedge r_clk or negedge r_rst_n) begin
        if (!r_rst_n) empty <= 1'b1;
        else          empty <= empty_next;
    end

endmodule

rtl/apb_fifo_async.sv
`timescale 1ns/1ps

module apb_fifo_async #(
    parameter int DW    = 8,
    parameter int DEPTH = 8
) (
    // APB interface (PCLK domain)
    input  logic PCLK,
    input  logic PRESETn,

    input  logic PSEL,
    input  logic PENABLE,
    input  logic PWRITE,
    input  logic [7:0]  PADDR,
    input  logic [31:0] PWDATA,

    output logic [31:0] PRDATA,
    output logic        PREADY,
    output logic        PSLVERR,

    // Async FIFO read domain interface
    input  logic         r_clk,
    input  logic         r_rst_n_in,
    input  logic         r_en_in,
    output logic [DW-1:0] r_data_out,
    output logic         empty_out,

    // expose write-side FULL for debug/integration
    output logic         full_out
);

    wire _unused_ok = &PWDATA[31:DW];

    // APB constants / decode
    localparam logic [7:0] ADDR_CTRL   = 8'h00;
    localparam logic [7:0] ADDR_STATUS = 8'h04;
    localparam logic [7:0] ADDR_WDATA  = 8'h08;

    // APB transfer detection (APB3):
    // setup phase: PSEL=1, PENABLE=0
    // access phase: PSEL=1, PENABLE=1
    logic apb_access;
    assign apb_access = PSEL && PENABLE;

    // Always-ready slave (zero wait states)
    assign PREADY  = 1'b1;
    assign PSLVERR = 1'b0;

    // Control/status regs (PCLK domain)
    logic en;
    logic ovf_sticky;

    // Soft reset pulse generated in PCLK domain, used to reset FIFO write domain.
    logic soft_reset_pulse;

    // Clear flags pulse
    logic clr_flags_pulse;

    // Write strobe for WDATA
    logic wdata_wr;
    assign wdata_wr = apb_access && PWRITE && (PADDR == ADDR_WDATA);

    // CTRL writes happen on access phase
    always_ff @(posedge PCLK or negedge PRESETn) begin
        if (!PRESETn) begin
            en               <= 1'b0;
            soft_reset_pulse <= 1'b0;
            clr_flags_pulse  <= 1'b0;
        end else begin
            // default: pulses low unless written
            soft_reset_pulse <= 1'b0;
            clr_flags_pulse  <= 1'b0;

            if (apb_access && PWRITE && (PADDR == ADDR_CTRL)) begin
                // bit0: EN (level)
                en <= PWDATA[0];

                // bit1: SOFT_RESET (write-one pulse)
                if (PWDATA[1])
                    soft_reset_pulse <= 1'b1;

                // bit2: CLR_FLAGS (write-one pulse)
                if (PWDATA[2])
                    clr_flags_pulse <= 1'b1;
            end
        end
    end

    // -------------------------
    // FIFO resets
    // -------------------------
    logic w_rst_n_fifo;
    logic r_rst_n_fifo;

    // Write reset is PRESETn AND not soft-reset pulse (pulse forces one-cycle reset)
    always_ff @(posedge PCLK or negedge PRESETn) begin
        if (!PRESETn) begin
            w_rst_n_fifo <= 1'b0;
        end else begin
            w_rst_n_fifo <= 1'b1;
            if (soft_reset_pulse)
                w_rst_n_fifo <= 1'b0;
        end
    end

    // Read reset: async assert, sync deassert (combines PRESETn and r_rst_n_in)
    wire r_rst_n_async = PRESETn & r_rst_n_in;

    logic r_rst_ff1, r_rst_ff2;
    always_ff @(posedge r_clk or negedge r_rst_n_async) begin
        if (!r_rst_n_async) begin
            r_rst_ff1 <= 1'b0;
            r_rst_ff2 <= 1'b0;
        end else begin
            r_rst_ff1 <= 1'b1;
            r_rst_ff2 <= r_rst_ff1;
        end
    end

    assign r_rst_n_fifo = r_rst_ff2;

    // -------------------------
    // FIFO ports
    // -------------------------
    logic         w_en_fifo;
    logic [DW-1:0] w_data_fifo;
    logic         full_fifo;

    logic         r_en_fifo;
    logic [DW-1:0] r_data_fifo;
    logic         empty_fifo;

    // Make it explicit that we only use the low DW bits (silences PWDATA[31:8] warning)
    wire [DW-1:0] apb_wdata = PWDATA[DW-1:0];

    // Drive FIFO write enable from APB WDATA writes
    assign w_en_fifo   = wdata_wr && en && !full_fifo;
    assign w_data_fifo = apb_wdata;

    // Pass-through read side
    assign r_en_fifo = r_en_in;

    fifo_async #(.DW(DW), .DEPTH(DEPTH)) u_fifo (
        .w_clk   (PCLK),
        .w_rst_n (w_rst_n_fifo),
        .w_en    (w_en_fifo),
        .w_data  (w_data_fifo),
        .full    (full_fifo),

        .r_clk   (r_clk),
        .r_rst_n (r_rst_n_fifo),
        .r_en    (r_en_fifo),
        .r_data  (r_data_fifo),
        .empty   (empty_fifo)
    );

    assign full_out   = full_fifo;
    assign empty_out  = empty_fifo;
    assign r_data_out = r_data_fifo;

    // Sticky overflow flag: APB attempted WDATA write while FULL
    always_ff @(posedge PCLK or negedge PRESETn) begin
        if (!PRESETn) begin
            ovf_sticky <= 1'b0;
        end else begin
            if (clr_flags_pulse)
                ovf_sticky <= 1'b0;
            else if (wdata_wr && en && full_fifo)
                ovf_sticky <= 1'b1;
        end
    end

    // APB read mux
    always_comb begin
        PRDATA = 32'h0;

        if (!PWRITE) begin
            unique case (PADDR)
                ADDR_CTRL: begin
                    PRDATA[0] = en;
                end
                ADDR_STATUS: begin
                    PRDATA[0] = empty_fifo;
                    PRDATA[1] = full_fifo;
                    PRDATA[2] = ovf_sticky;
                end
                default: begin
                    PRDATA = 32'h0;
                end
            endcase
        end
    end

endmodule

tb/tb_apb_fifo_async.sv
`timescale 1ns/1ps

module tb_apb_fifo_async;

    initial begin
        $dumpfile("waves.vcd");
        $dumpvars(0, tb_apb_fifo_async);
    end

    localparam int DW = 8;
    localparam int DEPTH = 8;

    // Clocks / resets
    logic PCLK, PRESETn;
    logic r_clk, r_rst_n_in;

    // -------------------------
    // APB signals
    // -------------------------
    logic        PSEL;
    logic        PENABLE;
    logic        PWRITE;
    logic [7:0]  PADDR;
    logic [31:0] PWDATA;

    wire  [31:0] PRDATA;
    wire         PREADY;
    wire         PSLVERR;

    // -------------------------
    // Read-side interface
    // -------------------------
    logic              r_en_in;
    wire  [DW-1:0]     r_data_out;
    wire               empty_out;
    wire               full_out;

    // DUT
    apb_fifo_async #(.DW(DW), .DEPTH(DEPTH)) dut (
        .PCLK    (PCLK),
        .PRESETn (PRESETn),
        .PSEL    (PSEL),
        .PENABLE (PENABLE),
        .PWRITE  (PWRITE),
        .PADDR   (PADDR),
        .PWDATA  (PWDATA),
        .PRDATA  (PRDATA),
        .PREADY  (PREADY),
        .PSLVERR (PSLVERR),

        .r_clk      (r_clk),
        .r_rst_n_in (r_rst_n_in),
        .r_en_in    (r_en_in),
        .r_data_out (r_data_out),
        .empty_out  (empty_out),
        .full_out   (full_out)
    );

    // Clocks (different rates)
    always #5  PCLK  = ~PCLK;   // 10ns period
    always #7  r_clk = ~r_clk;  // 14ns period

    // -------------------------
    // APB helpers (simple APB3-style)
    // Transfer happens on: PSEL=1 && PENABLE=1
    // -------------------------
    task automatic apb_write(input logic [7:0] addr, input logic [31:0] data);
        begin
            @(posedge PCLK);
            PADDR   = addr;
            PWDATA  = data;
            PWRITE  = 1'b1;
            PSEL    = 1'b1;
            PENABLE = 1'b0;

            @(posedge PCLK);
            PENABLE = 1'b1; // ACCESS phase

            @(posedge PCLK);
            // done
            PSEL    = 1'b0;
            PENABLE = 1'b0;
            PWRITE  = 1'b0;
            PADDR   = '0;
            PWDATA  = '0;
        end
    endtask

    task automatic apb_read(input logic [7:0] addr, output logic [31:0] data);
        begin
            @(posedge PCLK);
            PADDR   = addr;
            PWRITE  = 1'b0;
            PSEL    = 1'b1;
            PENABLE = 1'b0;

            @(posedge PCLK);
            PENABLE = 1'b1; // ACCESS phase

            @(posedge PCLK);
            data = PRDATA;

            PSEL    = 1'b0;
            PENABLE = 1'b0;
            PADDR   = '0;
        end
    endtask

    // -------------------------
    // Scoreboard for read checking
    // Compare one cycle after a successful read.
    // -------------------------
    byte  exp_q[$];
    logic r_fire, r_fire_d;
    byte  exp_front_d;

    assign r_fire = r_en_in && !empty_out;

    always_ff @(posedge r_clk or negedge r_rst_n_in) begin
        if (!r_rst_n_in) begin
            r_fire_d    <= 1'b0;
            exp_front_d <= '0;
        end else begin
            r_fire_d <= r_fire;

            if (r_fire) begin
                if (exp_q.size() == 0) begin
                    $display("ERROR: Read fired but scoreboard empty at t=%0t", $time);
                    $fatal(1);
                end
                exp_front_d <= exp_q.pop_front();
            end
        end
    end

    int read_ok_count;

    always_ff @(posedge r_clk or negedge r_rst_n_in) begin
        if (!r_rst_n_in) begin
            read_ok_count <= 0;
        end else if (r_fire_d) begin
            if (r_data_out !== exp_front_d) begin
                $display("ERROR: Data mismatch at t=%0t got=0x%0h exp=0x%0h",
                         $time, r_data_out, exp_front_d);
                $fatal(1);
            end else begin
                read_ok_count <= read_ok_count + 1;
                $display("OK: READ t=%0t data=0x%0h (remaining=%0d empty=%0b full=%0b)",
                         $time, r_data_out, exp_q.size(), empty_out, full_out);
            end
        end
    end

    // -------------------------
    // Test
    // -------------------------
    logic [31:0] st;

    initial begin
        // init
        PCLK       = 1'b0;
        r_clk      = 1'b0;

        PRESETn    = 1'b0;
        r_rst_n_in = 1'b0;

        PSEL       = 1'b0;
        PENABLE    = 1'b0;
        PWRITE     = 1'b0;
        PADDR      = '0;
        PWDATA     = '0;

        r_en_in    = 1'b0;

        // hold reset for a bit
        repeat (5) @(posedge PCLK);
        PRESETn    = 1'b1;
        r_rst_n_in = 1'b1;

        $display("RESET RELEASED at t=%0t", $time);

        // mark as "used" so Verilator stops warning
        if (PREADY !== 1'b1) $display("NOTE: PREADY=%0b (ignored in this TB)", PREADY);
        if (PSLVERR !== 1'b0) $display("WARN: PSLVERR=%0b", PSLVERR);

        // Enable the wrapper: CTRL bit0 = EN (CTRL @ 0x00)
        apb_write(8'h00, 32'h0000_0001);

        // Quick status read (STATUS @ 0x04)
        apb_read(8'h04, st);
        $display("STATUS after enable: 0x%08h (EMPTY=%0b FULL=%0b)",
                 st, st[0], st[1]);

        // Write 8 known bytes to WDATA @ 0x08
        for (int i = 0; i < 8; i++) begin
            byte val = byte'(8'(16 + i));
            exp_q.push_back(val);
            $display("APB WRITE: data=0x%0h", val);
            apb_write(8'h08, {24'h0, val});
        end

        // Let pointers sync across domains a bit
        repeat (6) @(posedge r_clk);

        // Drain: pulse r_en_in until we see 8 good reads
        while (read_ok_count < 8) begin
            @(posedge r_clk);
            r_en_in = (!empty_out) ? 1'b1 : 1'b0;

            // single-cycle pulse
            @(posedge r_clk);
            r_en_in = 1'b0;
        end

        // Final checks
        if (exp_q.size() != 0) begin
            $display("ERROR: Scoreboard not empty at end. remaining=%0d", exp_q.size());
            $fatal(1);
        end

        apb_read(8'h04, st);
        $display("FINAL STATUS: 0x%08h (EMPTY=%0b FULL=%0b OVF=%0b)",
                 st, st[0], st[1], st[2]);

        if (st[0] !== 1'b1) begin
            $display("ERROR: Expected EMPTY=1 at end");
            $fatal(1);
        end

        $display("PASS ✅  Wrote 8 bytes via APB and read them back in-order across CDC.");
        $finish;
    end

endmodule

wave.vcd
$version Generated by VerilatedVcd $end
$timescale 1ps $end
 $scope module tb_apb_fifo_async $end
  $var wire 32 \ DW [31:0] $end
  $var wire 32 \ DEPTH [31:0] $end
  $var wire 1 G PCLK $end
  $var wire 1 # PRESETn $end
  $var wire 1 H r_clk $end
  $var wire 1 $ r_rst_n_in $end
  $var wire 1 % PSEL $end
  $var wire 1 & PENABLE $end
  $var wire 1 ' PWRITE $end
  $var wire 8 ( PADDR [7:0] $end
  $var wire 32 ) PWDATA [31:0] $end
  $var wire 32 I PRDATA [31:0] $end
  $var wire 1 ] PREADY $end
  $var wire 1 ^ PSLVERR $end
  $var wire 1 * r_en_in $end
  $var wire 8 5 r_data_out [7:0] $end
  $var wire 1 6 empty_out $end
  $var wire 1 : full_out $end
  $var wire 1 J r_fire $end
  $var wire 1 / r_fire_d $end
  $var wire 8 0 exp_front_d [7:0] $end
  $var wire 32 1 read_ok_count [31:0] $end
  $var wire 32 + st [31:0] $end
  $scope module dut $end
   $var wire 32 \ DW [31:0] $end
   $var wire 32 \ DEPTH [31:0] $end
   $var wire 1 G PCLK $end
   $var wire 1 # PRESETn $end
   $var wire 1 % PSEL $end
   $var wire 1 & PENABLE $end
   $var wire 1 ' PWRITE $end
   $var wire 8 ( PADDR [7:0] $end
   $var wire 32 ) PWDATA [31:0] $end
   $var wire 32 I PRDATA [31:0] $end
   $var wire 1 ] PREADY $end
   $var wire 1 ^ PSLVERR $end
   $var wire 1 H r_clk $end
   $var wire 1 $ r_rst_n_in $end
   $var wire 1 * r_en_in $end
   $var wire 8 5 r_data_out [7:0] $end
   $var wire 1 6 empty_out $end
   $var wire 1 : full_out $end
   $var wire 8 _ ADDR_CTRL [7:0] $end
   $var wire 8 ` ADDR_STATUS [7:0] $end
   $var wire 8 a ADDR_WDATA [7:0] $end
   $var wire 1 K apb_access $end
   $var wire 1 2 en $end
   $var wire 1 3 ovf_sticky $end
   $var wire 1 L soft_reset_pulse $end
   $var wire 1 4 clr_flags_pulse $end
   $var wire 1 M wdata_wr $end
   $var wire 1 N w_rst_n_fifo $end
   $var wire 1 O r_rst_n_fifo $end
   $var wire 1 P r_rst_n_async $end
   $var wire 1 Q r_rst_ff1 $end
   $var wire 1 O r_rst_ff2 $end
   $var wire 1 R w_en_fifo $end
   $var wire 8 , w_data_fifo [7:0] $end
   $var wire 1 : full_fifo $end
   $var wire 1 * r_en_fifo $end
   $var wire 8 5 r_data_fifo [7:0] $end
   $var wire 1 6 empty_fifo $end
   $var wire 8 , apb_wdata [7:0] $end
   $scope module u_fifo $end
    $var wire 32 \ DW [31:0] $end
    $var wire 32 \ DEPTH [31:0] $end
    $var wire 1 G w_clk $end
    $var wire 1 N w_rst_n $end
    $var wire 1 R w_en $end
    $var wire 8 , w_data [7:0] $end
    $var wire 1 : full $end
    $var wire 1 H r_clk $end
    $var wire 1 O r_rst_n $end
    $var wire 1 * r_en $end
    $var wire 8 5 r_data [7:0] $end
    $var wire 1 6 empty $end
    $var wire 32 b AW [31:0] $end
    $var wire 32 c PW [31:0] $end
    $var wire 8 ; mem[0] [7:0] $end
    $var wire 8 < mem[1] [7:0] $end
    $var wire 8 = mem[2] [7:0] $end
    $var wire 8 > mem[3] [7:0] $end
    $var wire 8 ? mem[4] [7:0] $end
    $var wire 8 @ mem[5] [7:0] $end
    $var wire 8 A mem[6] [7:0] $end
    $var wire 8 B mem[7] [7:0] $end
    $var wire 4 S w_bin [3:0] $end
    $var wire 4 T w_bin_next [3:0] $end
    $var wire 4 C w_gray [3:0] $end
    $var wire 4 U w_gray_next [3:0] $end
    $var wire 4 7 r_bin [3:0] $end
    $var wire 4 V r_bin_next [3:0] $end
    $var wire 4 W r_gray [3:0] $end
    $var wire 4 X r_gray_next [3:0] $end
    $var wire 4 D r_gray_sync_w [3:0] $end
    $var wire 4 8 w_gray_sync_r [3:0] $end
    $var wire 1 Y full_next $end
    $var wire 1 Z empty_next $end
    $var wire 1 [ w_inc $end
    $var wire 1 J r_inc $end
    $var wire 4 E w_gray_full_cmp [3:0] $end
    $scope module u_sync_rptr_to_w $end
     $var wire 32 c W [31:0] $end
     $var wire 1 G clk $end
     $var wire 1 N rst_n $end
     $var wire 4 W d [3:0] $end
     $var wire 4 D q [3:0] $end
     $var wire 4 F q1 [3:0] $end
    $upscope $end
    $scope module u_sync_wptr_to_r $end
     $var wire 32 c W [31:0] $end
     $var wire 1 H clk $end
     $var wire 1 O rst_n $end
     $var wire 4 C d [3:0] $end
     $var wire 4 8 q [3:0] $end
     $var wire 4 9 q1 [3:0] $end
    $upscope $end
   $upscope $end
  $upscope $end
  $scope module unnamedblk1 $end
   $var wire 32 - i [31:0] $end
   $scope module unnamedblk2 $end
    $var wire 8 . val [7:0] $end
   $upscope $end
  $upscope $end
 $upscope $end
$enddefinitions $end


#0
0#
0$
0%
0&
0'
b00000000 (
b00000000000000000000000000000000 )
0*
b00000000000000000000000000000000 +
b00000000 ,
b00000000000000000000000000000000 -
b00000000 .
0/
b00000000 0
b00000000000000000000000000000000 1
02
03
04
b00000000 5
06
b0000 7
b0000 8
b0000 9
0:
b00000000 ;
b00000000 <
b00000000 =
b00000000 >
b00000000 ?
b00000000 @
b00000000 A
b00000000 B
b0000 C
b0000 D
b1100 E
b0000 F
0G
0H
b00000000000000000000000000000000 I
0J
0K
0L
0M
0N
0O
0P
0Q
0R
b0000 S
b0000 T
b0000 U
b0000 V
b0000 W
b0000 X
0Y
1Z
0[
b00000000000000000000000000001000 \
1]
0^
b00000000 _
b00000100 `
b00001000 a
b00000000000000000000000000000011 b
b00000000000000000000000000000100 c
#5000
1G
#7000
16
1H
#10000
0G
#14000
0H
#15000
1G
#20000
0G
#21000
1H
#25000
1G
#28000
0H
#30000
0G
#35000
1G
1H
#40000
0G
#42000
0H
#45000
1#
1$
1G
1N
1P
#49000
1H
1Q
#50000
0G
#55000
1%
1'
b00000000000000000000000000000001 )
b00000001 ,
1G
#56000
0H
#60000
0G
#63000
1H
1O
#65000
1&
12
1G
1K
#70000
0G
0H
#75000
0%
0&
0'
b00000000000000000000000000000000 )
b00000000 ,
1G
b00000000000000000000000000000001 I
0K
#77000
1H
#80000
0G
#84000
0H
#85000
1%
b00000100 (
1G
#90000
0G
#91000
1H
#95000
1&
1G
1K
#98000
0H
#100000
0G
#105000
0%
0&
b00000000 (
b00000000000000000000000000000001 +
b00010000 .
1G
1H
0K
#110000
0G
#112000
0H
#115000
1%
1'
b00001000 (
b00000000000000000000000000010000 )
b00010000 ,
1G
b00000000000000000000000000000000 I
#119000
1H
#120000
0G
#125000
1&
b00010000 ;
b0001 C
1G
1K
1M
1R
b0001 S
b0010 T
b0011 U
1[
#126000
0H
#130000
0G
#133000
b0001 9
1H
#135000
0%
0&
0'
b00000000 (
b00000000000000000000000000000000 )
b00000000 ,
b00000000000000000000000000000001 -
b00010001 .
1G
b00000000000000000000000000000001 I
0K
0M
0R
b0001 T
b0001 U
0[
#140000
0G
0H
#145000
1%
1'
b00001000 (
b00000000000000000000000000010001 )
b00010001 ,
1G
b00000000000000000000000000000000 I
#147000
b0001 8
1H
0Z
#150000
0G
#154000
0H
#155000
1&
b00010001 <
b0011 C
1G
1K
1M
1R
b0010 S
b0011 T
b0010 U
1[
#160000
0G
#161000
06
b0011 9
1H
#165000
0%
0&
0'
b00000000 (
b00000000000000000000000000000000 )
b00000000 ,
b00000000000000000000000000000010 -
b00010010 .
1G
b00000000000000000000000000000001 I
0K
0M
0R
b0010 T
b0011 U
0[
#168000
0H
#170000
0G
#175000
1%
1'
b00001000 (
b00000000000000000000000000010010 )
b00010010 ,
b0011 8
1G
1H
b00000000000000000000000000000000 I
#180000
0G
#182000
0H
#185000
1&
b00010010 =
b0010 C
1G
1K
1M
1R
b0011 S
b0100 T
b0110 U
1[
#189000
b0010 9
1H
#190000
0G
#195000
0%
0&
0'
b00000000 (
b00000000000000000000000000000000 )
b00000000 ,
b00000000000000000000000000000011 -
b00010011 .
1G
b00000000000000000000000000000001 I
0K
0M
0R
b0011 T
b0010 U
0[
#196000
0H
#200000
0G
#203000
b0010 8
1H
#205000
1%
1'
b00001000 (
b00000000000000000000000000010011 )
b00010011 ,
1G
b00000000000000000000000000000000 I
#210000
0G
0H
#215000
1&
b00010011 >
b0110 C
1G
1K
1M
1R
b0100 S
b0101 T
b0111 U
1[
#217000
b0110 9
1H
#220000
0G
#224000
0H
#225000
0%
0&
0'
b00000000 (
b00000000000000000000000000000000 )
b00000000 ,
b00000000000000000000000000000100 -
b00010100 .
1G
b00000000000000000000000000000001 I
0K
0M
0R
b0100 T
b0110 U
0[
#230000
0G
#231000
b0110 8
1H
#235000
1%
1'
b00001000 (
b00000000000000000000000000010100 )
b00010100 ,
1G
b00000000000000000000000000000000 I
#238000
0H
#240000
0G
#245000
1&
b00010100 ?
b0111 C
1G
1H
1K
1M
1R
b0101 S
b0110 T
b0101 U
1[
#250000
0G
#252000
0H
#255000
0%
0&
0'
b00000000 (
b00000000000000000000000000000000 )
b00000000 ,
b00000000000000000000000000000101 -
b00010101 .
1G
b00000000000000000000000000000001 I
0K
0M
0R
b0101 T
b0111 U
0[
#259000
b0111 9
1H
#260000
0G
#265000
1%
1'
b00001000 (
b00000000000000000000000000010101 )
b00010101 ,
1G
b00000000000000000000000000000000 I
#266000
0H
#270000
0G
#273000
b0111 8
1H
#275000
1&
b00010101 @
b0101 C
1G
1K
1M
1R
b0110 S
b0111 T
b0100 U
1[
#280000
0G
0H
#285000
0%
0&
0'
b00000000 (
b00000000000000000000000000000000 )
b00000000 ,
b00000000000000000000000000000110 -
b00010110 .
1G
b00000000000000000000000000000001 I
0K
0M
0R
b0110 T
b0101 U
0[
#287000
b0101 9
1H
#290000
0G
#294000
0H
#295000
1%
1'
b00001000 (
b00000000000000000000000000010110 )
b00010110 ,
1G
b00000000000000000000000000000000 I
#300000
0G
#301000
b0101 8
1H
#305000
1&
b00010110 A
b0100 C
1G
1K
1M
1R
b0111 S
b1000 T
b1100 U
1Y
1[
#308000
0H
#310000
0G
#315000
0%
0&
0'
b00000000 (
b00000000000000000000000000000000 )
b00000000 ,
b00000000000000000000000000000111 -
b00010111 .
b0100 9
1G
1H
b00000000000000000000000000000001 I
0K
0M
0R
b0111 T
b0100 U
0Y
0[
#320000
0G
#322000
0H
#325000
1%
1'
b00001000 (
b00000000000000000000000000010111 )
b00010111 ,
1G
b00000000000000000000000000000000 I
#329000
b0100 8
1H
#330000
0G
#335000
1&
1:
b00010111 B
b1100 C
1G
1K
1M
b1000 S
b1000 T
b1100 U
1Y
#336000
0H
#340000
0G
#343000
b1100 9
1H
#345000
0%
0&
0'
b00000000 (
b00000000000000000000000000000000 )
b00000000 ,
b00000000000000000000000000001000 -
1G
b00000000000000000000000000000001 I
0K
0M
#350000
0G
0H
#355000
1G
#357000
b1100 8
1H
#360000
0G
#364000
0H
#365000
1G
#370000
0G
#371000
1H
#375000
1G
#378000
0H
#380000
0G
#385000
1G
1H
#390000
0G
#392000
0H
#395000
1G
#399000
1H
#400000
0G
#405000
1G
#406000
0H
#410000
0G
#413000
1H
#415000
1G
#420000
0G
0H
#425000
1G
#427000
1H
#430000
0G
#434000
0H
#435000
1G
#440000
0G
#441000
1*
1/
b00010000 0
b00010000 5
b0001 7
1H
1J
b0010 V
b0001 W
b0011 X
#445000
b0001 F
1G
#448000
0H
#450000
0G
#455000
0*
0/
b00000000000000000000000000000001 1
b0001 D
b1101 E
1G
1H
0J
b0001 V
b0001 X
0Y
#460000
0G
#462000
0H
#465000
0:
1G
#469000
1*
1/
b00010001 0
b00010001 5
b0010 7
1H
1J
b0011 V
b0011 W
b0010 X
#470000
0G
#475000
b0011 F
1G
#476000
0H
#480000
0G
#483000
0*
0/
b00000000000000000000000000000010 1
1H
0J
b0010 V
b0011 X
#485000
b0011 D
b1111 E
1G
#490000
0G
0H
#495000
1G
#497000
1*
1/
b00010010 0
b00010010 5
b0011 7
1H
1J
b0100 V
b0010 W
b0110 X
#500000
0G
#504000
0H
#505000
b0010 F
1G
#510000
0G
#511000
0*
0/
b00000000000000000000000000000011 1
1H
0J
b0011 V
b0010 X
#515000
b0010 D
b1110 E
1G
#518000
0H
#520000
0G
#525000
1*
1/
b00010011 0
b00010011 5
b0100 7
1G
1H
1J
b0101 V
b0110 W
b0111 X
#530000
0G
#532000
0H
#535000
b0110 F
1G
#539000
0*
0/
b00000000000000000000000000000100 1
1H
0J
b0100 V
b0110 X
#540000
0G
#545000
b0110 D
b1010 E
1G
#546000
0H
#550000
0G
#553000
1*
1/
b00010100 0
b00010100 5
b0101 7
1H
1J
b0110 V
b0111 W
b0101 X
#555000
b0111 F
1G
#560000
0G
0H
#565000
b0111 D
b1011 E
1G
#567000
0*
0/
b00000000000000000000000000000101 1
1H
0J
b0101 V
b0111 X
#570000
0G
#574000
0H
#575000
1G
#580000
0G
#581000
1*
1/
b00010101 0
b00010101 5
b0110 7
1H
1J
b0111 V
b0101 W
b0100 X
#585000
b0101 F
1G
#588000
0H
#590000
0G
#595000
0*
0/
b00000000000000000000000000000110 1
b0101 D
b1001 E
1G
1H
0J
b0110 V
b0101 X
#600000
0G
#602000
0H
#605000
1G
#609000
1*
1/
b00010110 0
b00010110 5
b0111 7
1H
1J
b1000 V
b0100 W
b1100 X
1Z
#610000
0G
#615000
b0100 F
1G
#616000
0H
#620000
0G
#623000
0*
0/
b00000000000000000000000000000111 1
1H
0J
b0111 V
b0100 X
0Z
#625000
b0100 D
b1000 E
1G
#630000
0G
0H
#635000
1G
#637000
1*
1/
b00010111 0
b00010111 5
16
b1000 7
1H
b1000 V
b1100 W
b1100 X
1Z
#640000
0G
#644000
0H
#645000
b1100 F
1G
#650000
0G
#651000
0*
0/
b00000000000000000000000000001000 1
1H
#655000
b1100 D
b0000 E
1G
#658000
0H
#660000
0G
#665000
1G
1H
#670000
0G
#672000
0H
#675000
1G
#679000
1H
#680000
0G
#685000
1%
b00000100 (
1G
#686000
0H
#690000
0G
#693000
1H
#695000
1&
1G
1K
#700000
0G
0H
#705000
0%
0&
b00000000 (
1G
0K
